hydsensread/__init__.py
hydsensread/file_example/011704_1972-1974.csv
hydsensread/file_example/2026236_F4_20160222_2016_06_24.xle
hydsensread/file_example/2029499_F7_NordChamp_PL20150925_2015_09_25.xle
hydsensread/file_example/2041929_PO-06_XM20170307_2017_03_07.lev
hydsensread/file_example/2041929_PO-06_XM20170307_2017_03_07Compensated.lev
hydsensread/file_example/2056794_PO-05_baro_CB20161109_2016_11_09.lev
hydsensread/file_example/B653824V1-R2016-08-18_16-31-39_N001.xls
hydsensread/file_example/B656097V1-R2016-08-31_16-20-01_N001.xls
hydsensread/file_example/BEAUCEVILLE (7020560)_1980-2016.out
hydsensread/file_example/Brome (03030011).csv
hydsensread/file_example/F21_logger_20160224_20160621.csv
hydsensread/file_example/F2_20160223.lev
hydsensread/file_example/LOG001_1011105528.xls
hydsensread/file_example/LOG002_0504093718.xls
hydsensread/file_example/LOG006_0621113447.xls
hydsensread/file_example/PO-03_F2_XM20170222.dat
hydsensread/file_example/__init__.py
hydsensread/file_example/cr_file_example.dat
hydsensread/file_example/hydrolab_file.txt
hydsensread/file_example/maxxam_sheet.xlsx
hydsensread/file_example/slug_PO-05_20160729_1600.csv
hydsensread/file_parser/__init__.py
hydsensread/file_parser/abstract_file_parser.py
hydsensread/file_parser/concrete_file_parser.py
hydsensread/file_reader/__init__.py
hydsensread/file_reader/abstract_file_reader.py
hydsensread/file_reader/compagny_file_reader/__init__.py
hydsensread/file_reader/compagny_file_reader/campbell_cr_file_reader.py
hydsensread/file_reader/compagny_file_reader/hanna_file_reader.py
hydsensread/file_reader/compagny_file_reader/hydrolab_file_reader.py
hydsensread/file_reader/compagny_file_reader/maxxam_file_reader.py
hydsensread/file_reader/compagny_file_reader/solinst_file_reader.py
hydsensread/file_reader/compagny_file_reader/what_csv_file_reader.py
hydsensread/file_reader/compagny_file_reader/tests/files/1XXXXXX_solinst_levelogger_gold.csv
HydroSensorReader-1.7.6.dist-info/LICENSE
HydroSensorReader-1.7.6.dist-info/METADATA
HydroSensorReader-1.7.6.dist-info/WHEEL
HydroSensorReader-1.7.6.dist-info/top_level.txt
HydroSensorReader-1.7.6.dist-info/RECORD
