Metadata-Version: 2.1
Name: HydroSensorReader
Version: 1.7.6
Summary: Tools to read files from probes, sensors, or anything used in hydrogeology.
Home-page: https://github.com/cgq-qgc/HydroSensorReader
Author: Xavier Malet
Author-email: maletxa@gmail.com
License: MIT
Platform: UNKNOWN
Classifier: License :: OSI Approved :: MIT License
Classifier: Programming Language :: Python :: 3
Classifier: Operating System :: OS Independent
Requires-Dist: beautifulsoup4 (>=4.6.0)
Requires-Dist: requests (>=2.18.4)
Requires-Dist: openpyxl (>=2.4.8)
Requires-Dist: xlrd (>=1.1.0)
Requires-Dist: xlwt (>=1.3.0)
Requires-Dist: matplotlib
Requires-Dist: numpy
Requires-Dist: pandas (>=0.22.0)
